{
  "cislo_konania_spisu": "OU-BA-OSZP3-2025/300684",
  "cislo_rozhodnutia": null,
  "datum_dokumentu": "2025-05-27",
  "datum_zverejnenia": null,
  "lehoty_na_vyjadrenie": "v lehote 10 pracovných dní od doručenia tejto výzvy",
  "ziadatel_navrhovatel": null,
  "miesto_realizacie": {
    "kraj": null,
    "okres": "Bratislava",
    "obec": "Bratislava",
    "katastralne_uzemia": [],
    "parcely": [],
    "nazov_lokality": null
  },
  "typ_dokumentu": "VEREJNÁ VYHLÁŠKA",
  "typ_zasahu": [
    "neviem"
  ],
  "typ_uzemia": [
    "neviem"
  ],
  "je_v_chranenom_uzemi": null,
  "dotknute_zivocichy_rastliny": [],
  "odkaz_enviroportal": null,
  "zhrnutie": "Verejná vyhláška Okresného úradu Bratislava, odboru starostlivosti o životné prostredie, informujúca o doposlaní upovedomenia o proteste prokurátora v bližšie nešpecifikovanom konaní. Účastníci konania sú vyzvaní, aby sa k protestu vyjadrili v lehote 10 pracovných dní od doručenia výzvy. Dokument sa netýka konkrétneho typu zásahu, miesta realizácie, chránených území ani druhov, ktoré by boli identifikovateľné z tohto textu."
}